<?xml version="1.0" encoding="UTF-8" ?><tv date="20251223">
<channel id="TokyoMX1.jp"><display-name>Tokyo MX1</display-name><icon src="https://i.imgur.com/igia8OX.png"/><url>https://s.mxtv.jp</url></channel>
<channel id="TokyoMX2.jp"><display-name>Tokyo MX2</display-name><icon src="https://i.imgur.com/SwvuR00.png"/><url>https://s.mxtv.jp</url></channel>
<programme start="20251222200000 +0000" stop="20251222210000 +0000" channel="TokyoMX2.jp"><title lang="ja">ヒーリングタイム＆ヘッドラインニュース</title><desc lang="ja">レトロな気分</desc></programme>
<programme start="20251222210000 +0000" stop="20251222220000 +0000" channel="TokyoMX2.jp"><title lang="ja">ヒーリングタイム＆ヘッドラインニュース</title><desc lang="ja">路面電車のある風景 その２</desc></programme>
<programme start="20251222220000 +0000" stop="20251222220800 +0000" channel="TokyoMX2.jp"><title lang="ja">ヒーリングタイム＆ヘッドラインニュース</title><desc lang="ja">ねこの足跡＆看板猫編</desc></programme>
<programme start="20251222220800 +0000" stop="20251222223000 +0000" channel="TokyoMX2.jp"><title lang="ja">ごりやくさん【再】【字】</title><desc lang="ja">飛騨一宮水無神社</desc></programme>
<programme start="20251222223000 +0000" stop="20251222230000 +0000" channel="TokyoMX2.jp"><title lang="ja">ＭＸショッピング</title><desc lang="ja"/></programme>
<programme start="20251222230000 +0000" stop="20251222233000 +0000" channel="TokyoMX2.jp"><title lang="ja">ヒーリングタイム＆ヘッドラインニュース</title><desc lang="ja">散歩の風景 墨田・台東・日本橋・東京ＢＡＹ</desc></programme>
<programme start="20251222233000 +0000" stop="20251223024000 +0000" channel="TokyoMX2.jp"><title lang="ja">東京マーケットワイド 第１部【デ】</title><desc lang="ja">東証アローズから市況を完全生中継！プライム・スタンダード・グロースなど各市場の個別銘柄の値動きをリアルタイムで解説。アナリストが相場動向を分析、企業の最新情報も</desc></programme>
<programme start="20251223024000 +0000" stop="20251223030500 +0000" channel="TokyoMX2.jp"><title lang="ja">企業魂</title><desc lang="ja">銀座さいとう法律事務所</desc></programme>
<programme start="20251223030500 +0000" stop="20251223032900 +0000" channel="TokyoMX2.jp"><title lang="ja">ヒーリングタイム＆ヘッドラインニュース</title><desc lang="ja">【改】Ａｒｔｉｓｔ</desc></programme>
<programme start="20251223032900 +0000" stop="20251223065000 +0000" channel="TokyoMX2.jp"><title lang="ja">東京マーケットワイド 第２部【デ】</title><desc lang="ja">東証アローズから市況を完全生中継！プライム・スタンダード・グロースなど各市場の個別銘柄の値動きをリアルタイムで解説。アナリストが相場動向を分析、企業の最新情報も</desc></programme>
<programme start="20251223065000 +0000" stop="20251223080000 +0000" channel="TokyoMX2.jp"><title lang="ja">ヒーリングタイム＆ヘッドラインニュース</title><desc lang="ja">散歩の風景 北総／浪漫点描 散歩の風景 初夏１</desc></programme>
<programme start="20251223080000 +0000" stop="20251223080800 +0000" channel="TokyoMX2.jp"><title lang="ja">ヒーリングタイム＆ヘッドラインニュース</title><desc lang="ja">東京点描 谷中・根津・千駄木</desc></programme>
<programme start="20251223080800 +0000" stop="20251223083000 +0000" channel="TokyoMX2.jp"><title lang="ja">ごりやくさん【再】【字】</title><desc lang="ja">近江神宮</desc></programme>
<programme start="20251223083000 +0000" stop="20251223090000 +0000" channel="TokyoMX2.jp"><title lang="ja">ＭＸショッピング</title><desc lang="ja"/></programme>
<programme start="20251223090000 +0000" stop="20251223093000 +0000" channel="TokyoMX2.jp"><title lang="ja">ＭＸショッピング</title><desc lang="ja"/></programme>
<programme start="20251223093000 +0000" stop="20251223093800 +0000" channel="TokyoMX2.jp"><title lang="ja">ヒーリングタイム＆ヘッドラインニュース</title><desc lang="ja">ねこの足跡</desc></programme>
<programme start="20251223093800 +0000" stop="20251223100000 +0000" channel="TokyoMX2.jp"><title lang="ja">ごりやくさん【再】【字】</title><desc lang="ja">太宰府天満宮</desc></programme>
<programme start="20251223100000 +0000" stop="20251223103000 +0000" channel="TokyoMX2.jp"><title lang="ja">ＭＸショッピング</title><desc lang="ja"/></programme>
<programme start="20251223103000 +0000" stop="20251223110000 +0000" channel="TokyoMX2.jp"><title lang="ja">ＭＸショッピング</title><desc lang="ja"/></programme>
<programme start="20251223110000 +0000" stop="20251223110900 +0000" channel="TokyoMX2.jp"><title lang="ja">ヒーリングタイム＆ヘッドラインニュース</title><desc lang="ja">散歩の風景 池上線の通る街角</desc></programme>
<programme start="20251223110900 +0000" stop="20251223120000 +0000" channel="TokyoMX2.jp"><title lang="ja">銭形平次 ★第７６２話「娘せんせい奮斗記」</title><desc lang="ja">昭和を代表するご存知大人気テレビ時代劇！</desc></programme>
<programme start="20251223120000 +0000" stop="20251223123000 +0000" channel="TokyoMX2.jp"><title lang="ja">ＭＸショッピング</title><desc lang="ja"/></programme>
<programme start="20251223123000 +0000" stop="20251223130000 +0000" channel="TokyoMX2.jp"><title lang="ja">ＭＸショッピング</title><desc lang="ja"/></programme>
<programme start="20251223130000 +0000" stop="20251223140000 +0000" channel="TokyoMX2.jp"><title lang="ja">ＷＯＲＬＤ ＭＡＲＫＥＴＺ</title><desc lang="ja">国内夜間取引・為替市場・欧州株式市場・米国株式市場の動向をＬＩＶＥで解説</desc></programme>
<programme start="20251223140000 +0000" stop="20251223143000 +0000" channel="TokyoMX2.jp"><title lang="ja">Ｔｏｋｙｏ　Ｐｈｏｔｏ　Ｌｉｂｒａｒｙ</title><desc lang="ja">２両の電車が行く西新井大師</desc></programme>
<programme start="20251223143000 +0000" stop="20251223150000 +0000" channel="TokyoMX2.jp"><title lang="ja">Ｔｏｋｙｏ　Ｐｈｏｔｏ　Ｌｉｂｒａｒｙ</title><desc lang="ja">緑と影のコントラスト、武蔵境</desc></programme>
<programme start="20251223150000 +0000" stop="20251223153000 +0000" channel="TokyoMX2.jp"><title lang="ja">ヒーリングタイム＆ヘッドラインニュース</title><desc lang="ja">ブリキの時間箱②</desc></programme>
<programme start="20251223153000 +0000" stop="20251223160000 +0000" channel="TokyoMX2.jp"><title lang="ja">ヒーリングタイム＆ヘッドラインニュース</title><desc lang="ja">ブリキの時間箱②</desc></programme>
<programme start="20251223160000 +0000" stop="20251223170000 +0000" channel="TokyoMX2.jp"><title lang="ja">ヒーリングタイム＆ヘッドラインニュース</title><desc lang="ja">東京点描 上野そして芝</desc></programme>
<programme start="20251223170000 +0000" stop="20251223180000 +0000" channel="TokyoMX2.jp"><title lang="ja">ヒーリングタイム＆ヘッドラインニュース</title><desc lang="ja">東京ＢＡＹクルーズ</desc></programme>
<programme start="20251223180000 +0000" stop="20251223190000 +0000" channel="TokyoMX2.jp"><title lang="ja">ヒーリングタイム＆ヘッドラインニュース</title><desc lang="ja">江戸川区自然動物園</desc></programme>
<programme start="20251223190000 +0000" stop="20251223200000 +0000" channel="TokyoMX2.jp"><title lang="ja">ヒーリングタイム＆ヘッドラインニュース</title><desc lang="ja">東京点描 城西２</desc></programme>
<programme start="20251222200000 +0000" stop="20251222200500 +0000" channel="TokyoMX1.jp"><title lang="ja">ハッピーナッチョイ！</title><desc lang="ja">「コロナが明けたら、出掛けよう、誰かに会いに行こう」のメッセージを込めたミニアニメ！作品を通じてコロナ禍の子どもたちを応援します！</desc></programme>
<programme start="20251222200500 +0000" stop="20251222210000 +0000" channel="TokyoMX1.jp"><title lang="ja">昔の男 ★第１２話「心臓も凍る結末」【再】【終】</title><desc lang="ja"/></programme>
<programme start="20251222210000 +0000" stop="20251222220000 +0000" channel="TokyoMX1.jp"><title lang="ja">ショップチャンネル お買い物エンターテインメント</title><desc lang="ja">国内外の商品を生放送でご紹介。ここでしか買えないレアなアイテムや、人気のブランドのアイテムなど、バラエティ豊かに登場しますので、お見逃しなく！</desc></programme>
<programme start="20251222220000 +0000" stop="20251222223000 +0000" channel="TokyoMX1.jp"><title lang="ja">欲しがり女子と、訳あり男子。 ＃３、＃４</title><desc lang="ja">田口淳之介の１１年ぶり地上波作品！「訳あり」男子を熱演▼パク・ユチョンの不思議な役柄とは…？▼主人公が生きる意欲を取り戻す、恋愛再生コメディストーリー！</desc></programme>
<programme start="20251222223000 +0000" stop="20251222223500 +0000" channel="TokyoMX1.jp"><title lang="ja">ハッピーナッチョイ！</title><desc lang="ja">「コロナが明けたら、出掛けよう、誰かに会いに行こう」のメッセージを込めたミニアニメ！作品を通じてコロナ禍の子どもたちを応援します！</desc></programme>
<programme start="20251222223500 +0000" stop="20251222230000 +0000" channel="TokyoMX1.jp"><title lang="ja">原日出子の京さんぽ ★「下立売通」</title><desc lang="ja">京都が大好きな原日出子が、碁盤の目のような京都の「通り」をお散歩しながら、通りの個性、店、そして出会う人々などを紹介していきます。</desc></programme>
<programme start="20251222230000 +0000" stop="20251222233000 +0000" channel="TokyoMX1.jp"><title lang="ja">ＭＸショッピング</title><desc lang="ja"/></programme>
<programme start="20251222233000 +0000" stop="20251223000000 +0000" channel="TokyoMX1.jp"><title lang="ja">ＭＸショッピング</title><desc lang="ja"/></programme>
<programme start="20251223000000 +0000" stop="20251223010000 +0000" channel="TokyoMX1.jp"><title lang="ja">有翡（ゆうひ）－Ｌｅｇｅｎｄ ｏｆ Ｌｏｖｅ－ ★第３８話「夜明け前」〔字幕スーパー〕</title><desc lang="ja">「楚喬伝（そきょうでん）～いばらに咲く花～」のチャオ・リーインと「陳情令」のワン・イーボー、２大トップスターが共演！</desc></programme>
<programme start="20251223010000 +0000" stop="20251223013000 +0000" channel="TokyoMX1.jp"><title lang="ja">ＭＸショッピング</title><desc lang="ja"/></programme>
<programme start="20251223013000 +0000" stop="20251223020000 +0000" channel="TokyoMX1.jp"><title lang="ja">お買い物情報</title><desc lang="ja"/></programme>
<programme start="20251223020000 +0000" stop="20251223020400 +0000" channel="TokyoMX1.jp"><title lang="ja">ＴＯＫＹＯ ＭＸ ＮＥＷＳ</title><desc lang="ja">東京の様々なニュースをお伝えします。</desc></programme>
<programme start="20251223020400 +0000" stop="20251223030000 +0000" channel="TokyoMX1.jp"><title lang="ja">灼灼風流～宮中に咲く愛の華～ ★第２４話「祖父の遺言」〔字幕スーパー〕</title><desc lang="ja">ウィリアム・フォン×大ヒットドラマのスタッフで贈る身分を超えた愛の花が咲く、珠玉のラブロマンス時代劇！</desc></programme>
<programme start="20251223030000 +0000" stop="20251223033000 +0000" channel="TokyoMX1.jp"><title lang="ja">ＭＸショッピング</title><desc lang="ja"/></programme>
<programme start="20251223033000 +0000" stop="20251223040000 +0000" channel="TokyoMX1.jp"><title lang="ja">ＭＸショッピング</title><desc lang="ja"/></programme>
<programme start="20251223040000 +0000" stop="20251223040400 +0000" channel="TokyoMX1.jp"><title lang="ja">ＴＯＫＹＯ ＭＸ ＮＥＷＳ</title><desc lang="ja">東京の様々なニュースをお伝えします。</desc></programme>
<programme start="20251223040400 +0000" stop="20251223050000 +0000" channel="TokyoMX1.jp"><title lang="ja">帝王の娘スベクヒャン ★第３話〔字幕スーパー〕【二】</title><desc lang="ja">帝王の娘である“スベクヒャン”の座をめぐり異父姉妹の運命が交錯する</desc></programme>
<programme start="20251223050000 +0000" stop="20251223053000 +0000" channel="TokyoMX1.jp"><title lang="ja">ＭＸショッピング</title><desc lang="ja"/></programme>
<programme start="20251223053000 +0000" stop="20251223055900 +0000" channel="TokyoMX1.jp"><title lang="ja">ＭＸショッピング</title><desc lang="ja"/></programme>
<programme start="20251223055900 +0000" stop="20251223060000 +0000" channel="TokyoMX1.jp"><title lang="ja">フラッシュ天気（初音ミク「マジカルミライ」ｖｅｒ．）</title><desc lang="ja"/></programme>
<programme start="20251223060000 +0000" stop="20251223060400 +0000" channel="TokyoMX1.jp"><title lang="ja">ＴＯＫＹＯ ＭＸ ＮＥＷＳ</title><desc lang="ja">東京の様々なニュースをお伝えします。</desc></programme>
<programme start="20251223060400 +0000" stop="20251223070000 +0000" channel="TokyoMX1.jp"><title lang="ja">必殺商売人 ★第１９話「親にないしょの片道切符」</title><desc lang="ja">“必殺シリーズ”第１２弾！ご存知、中村主水（藤田まこと）６度目の登場。草笛光子、梅宮辰夫、火野正平らとみせる殺しの冴え！</desc></programme>
<programme start="20251223070000 +0000" stop="20251223073000 +0000" channel="TokyoMX1.jp"><title lang="ja">ＭＸショッピング</title><desc lang="ja"/></programme>
<programme start="20251223073000 +0000" stop="20251223080000 +0000" channel="TokyoMX1.jp"><title lang="ja">ＭＸショッピング</title><desc lang="ja"/></programme>
<programme start="20251223080000 +0000" stop="20251223083000 +0000" channel="TokyoMX1.jp"><title lang="ja">ＭＸショッピング</title><desc lang="ja"/></programme>
<programme start="20251223083000 +0000" stop="20251223085900 +0000" channel="TokyoMX1.jp"><title lang="ja">【新】サクマ＆ピース シーズン５ ＃１「空飛ぶ！けんか祭り編」</title><desc lang="ja">テレビプロデューサーの佐久間宣行、アルコ＆ピースの平子祐希。福島が誇る日本を代表するヒト、モノに出会い全国に広まるようにプロデュースする街ぶらバラエティ第５弾</desc></programme>
<programme start="20251223085900 +0000" stop="20251223093000 +0000" channel="TokyoMX1.jp"><title lang="ja">尾形春水のＨａｒｕｎａｔｉｏｎ ＴＶ</title><desc lang="ja">若くしてトップアイドルに上り詰め、その後も激動の芸能人生を歩んできた尾形春水の様々な挑戦を追う。</desc></programme>
<programme start="20251223093000 +0000" stop="20251223100000 +0000" channel="TokyoMX1.jp"><title lang="ja">トムとジェリー ショー＜セカンド・シーズン＞ ＃２３【二】</title><desc lang="ja">＃２４「人気者はつらいよ」「子ネコにムチュー」「トムの憂うつ」</desc></programme>
<programme start="20251223100000 +0000" stop="20251223103000 +0000" channel="TokyoMX1.jp"><title lang="ja">【放送開始２５周年記念】仮面ライダークウガ ＃３４「戦慄」</title><desc lang="ja"/></programme>
<programme start="20251223103000 +0000" stop="20251223110000 +0000" channel="TokyoMX1.jp"><title lang="ja">デジモンテイマーズ ＃２９「ここは幽霊の城！迷えるクルモン大脱出」</title><desc lang="ja">カードスラッシュ！キミもテイマーを目指せ！</desc></programme>
<programme start="20251223110000 +0000" stop="20251223120000 +0000" channel="TokyoMX1.jp"><title lang="ja">【生】堀潤 Ｌｉｖｅ Ｊｕｎｃｔｉｏｎ ★浅草・伝法院通りの店舗“不法占拠”問題和解</title><desc lang="ja">ジャーナリスト堀潤が独自目線で伝える報道番組▼原発再稼働巡り新潟県議会の判断は▼ふかわりょう／金子恵美／荻原博子／キャスター・豊崎由里絵／気象予報士・井澤咲乃</desc></programme>
<programme start="20251223120000 +0000" stop="20251223122500 +0000" channel="TokyoMX1.jp"><title lang="ja">うたごえはミルフィーユ ＃８「放物線」【再】</title><desc lang="ja"/></programme>
<programme start="20251223122500 +0000" stop="20251223125400 +0000" channel="TokyoMX1.jp"><title lang="ja">野田クリの野望～ゲーム天下統一への道～ ★しんやの家で忘年会？懐かし６４バトル【再】</title><desc lang="ja">今年最後の撮りおろし放送！スタジオにしんやの部屋（？）再現懐かし６４ソフト「マリオカート６４」「マリオテニス６４」「カスタムロボＶ２」で子どもみたいに大揉め!?</desc></programme>
<programme start="20251223125400 +0000" stop="20251223130000 +0000" channel="TokyoMX1.jp"><title lang="ja">ピカイチくん！</title><desc lang="ja">お酒の飲みすぎと免疫力</desc></programme>
<programme start="20251223130000 +0000" stop="20251223132900 +0000" channel="TokyoMX1.jp"><title lang="ja">アニメの神様『ドラゴンボールＺ』 ＃２８９「悟空おじちゃん！私がパンよ!!」【再】</title><desc lang="ja"/></programme>
<programme start="20251223132900 +0000" stop="20251223140000 +0000" channel="TokyoMX1.jp"><title lang="ja">アニメの神様『機動戦士ガンダムＳＥＥＤ ＤＥＳＴＩＮＹ ＨＤリマスター』 ＃５０</title><desc lang="ja">＃５０「最後の力」</desc></programme>
<programme start="20251223140000 +0000" stop="20251223143000 +0000" channel="TokyoMX1.jp"><title lang="ja">モンスターストライク　デッドバースリローデッド　＃１０【終】【字】</title><desc lang="ja">モンストアニメの新シリーズ。世界の終りで私たちは出会ったーー</desc></programme>
<programme start="20251223143000 +0000" stop="20251223150000 +0000" channel="TokyoMX1.jp"><title lang="ja">キミと越えて恋になる　★ｅｐｉｓｏｄｅ１１</title><desc lang="ja">どんな壁もキミとなら越えていける</desc></programme>
<programme start="20251223150000 +0000" stop="20251223153000 +0000" channel="TokyoMX1.jp"><title lang="ja">小峠英二のなんて美だ！</title><desc lang="ja">初心者でもアートについて簡単に学べる“日本一敷居の低いアートバラエティ番組” 小峠英二＆アートディレクター・中谷日出＆乃木坂４６・池田瑛紗と共にアートを学ぼう！</desc></programme>
<programme start="20251223153000 +0000" stop="20251223160000 +0000" channel="TokyoMX1.jp"><title lang="ja">千歳くんはラムネ瓶のなか　＃９「名前のあるカンケイと名前のないキョリ」</title><desc lang="ja">《このライトノベルがすごい！》殿堂入り作品、ついにＴＶアニメ化！福井を舞台に紡がれる、どこまでも青く、どこまでも眩しい、エモーショナル青春ストーリー！</desc></programme>
<programme start="20251223160000 +0000" stop="20251223160500 +0000" channel="TokyoMX1.jp"><title lang="ja">あおぎり高校のＥＮＪＯＹ！エンジョー予備校！　＃１１「誉め言葉がディスりに!?」【再】</title><desc lang="ja">あなたは明日「炎上」するかも!?これは、決して脅しじゃぁ～ない！令和の必修科目、「炎上対策」を「おもしろければ何でもあり」なあおぎり高校と一緒に学ぼう～！</desc></programme>
<programme start="20251223160500 +0000" stop="20251223163500 +0000" channel="TokyoMX1.jp"><title lang="ja">うしおととら　＃２０「妖、帰還す」【再】</title><desc lang="ja"/></programme>
<programme start="20251223163500 +0000" stop="20251223170500 +0000" channel="TokyoMX1.jp"><title lang="ja">ケンドーコバヤシのキャベリバ内閣　★ゲスト／藤本敏史（ＦＵＪＩＷＡＲＡ）</title><desc lang="ja">トップキャストの限界を探る「ＮＧの境界線」！▼先月の給料は!?▼乳輪の色は!?▼口説かれた有名人は!?</desc></programme>
<programme start="20251223170500 +0000" stop="20251223173400 +0000" channel="TokyoMX1.jp"><title lang="ja">関内デビル</title><desc lang="ja">舞台は横浜・関内にある喫茶店「関内デビル」。マスターの大場英治とアルバイトの私立恵比寿中学が働くこの店に常連客の中島来弥が来店。様々なトークを繰り広げる。</desc></programme>
<programme start="20251223173400 +0000" stop="20251223173500 +0000" channel="TokyoMX1.jp"><title lang="ja">フラッシュ天気（初音ミク「マジカルミライ」ｖｅｒ．）</title><desc lang="ja"/></programme>
<programme start="20251223173500 +0000" stop="20251223180500 +0000" channel="TokyoMX1.jp"><title lang="ja">ＭＸショッピング</title><desc lang="ja"/></programme>
<programme start="20251223180500 +0000" stop="20251223183500 +0000" channel="TokyoMX1.jp"><title lang="ja">ＭＸショッピング</title><desc lang="ja"/></programme>
<programme start="20251223183500 +0000" stop="20251223190000 +0000" channel="TokyoMX1.jp"><title lang="ja">洋上の楽園クルーズ【再】</title><desc lang="ja">「のどかな田園風景と美食を味わうドナウ川の旅」</desc></programme>
<programme start="20251223190000 +0000" stop="20251223193000 +0000" channel="TokyoMX1.jp"><title lang="ja">Ｍｕｓｉｃ　Ｂ．Ｂ．Ｊａｐａｎ</title><desc lang="ja"/></programme>
<programme start="20251223193000 +0000" stop="20251223200000 +0000" channel="TokyoMX1.jp"><title lang="ja">うたなびＭＡＸ！！</title><desc lang="ja"/></programme>
</tv>